odoo/addons/crm_salesperson_planner_sale/README.rst
odoo/addons/crm_salesperson_planner_sale/__init__.py
odoo/addons/crm_salesperson_planner_sale/__manifest__.py
odoo/addons/crm_salesperson_planner_sale/i18n/crm_salesperson_planner_sale.pot
odoo/addons/crm_salesperson_planner_sale/i18n/es.po
odoo/addons/crm_salesperson_planner_sale/i18n/it.po
odoo/addons/crm_salesperson_planner_sale/models/__init__.py
odoo/addons/crm_salesperson_planner_sale/models/crm_salesperson_planner_visit.py
odoo/addons/crm_salesperson_planner_sale/models/sale_order.py
odoo/addons/crm_salesperson_planner_sale/readme/CONTRIBUTORS.rst
odoo/addons/crm_salesperson_planner_sale/readme/DESCRIPTION.rst
odoo/addons/crm_salesperson_planner_sale/readme/USAGE.rst
odoo/addons/crm_salesperson_planner_sale/static/description/icon.png
odoo/addons/crm_salesperson_planner_sale/static/description/index.html
odoo/addons/crm_salesperson_planner_sale/tests/__init__.py
odoo/addons/crm_salesperson_planner_sale/tests/test_crm_salesperson_planner_sale.py
odoo/addons/crm_salesperson_planner_sale/views/crm_salesperson_planner_visit_views.xml
odoo/addons/crm_salesperson_planner_sale/views/sale_order_views.xml
odoo_addon_crm_salesperson_planner_sale-16.0.1.0.0.3.dist-info/METADATA
odoo_addon_crm_salesperson_planner_sale-16.0.1.0.0.3.dist-info/WHEEL
odoo_addon_crm_salesperson_planner_sale-16.0.1.0.0.3.dist-info/top_level.txt
odoo_addon_crm_salesperson_planner_sale-16.0.1.0.0.3.dist-info/RECORD
