Metadata-Version: 2.1
Name: odoo-addon-crm-salesperson-planner-sale
Version: 16.0.1.0.0.3
Summary: Crm Salesperson Planner Sale
Home-page: https://github.com/OCA/crm
Author: Sygel Technology, Tecnativa, Odoo Community Association (OCA)
Author-email: support@odoo-community.org
License: AGPL-3
Platform: UNKNOWN
Classifier: Programming Language :: Python
Classifier: Framework :: Odoo
Classifier: Framework :: Odoo :: 16.0
Classifier: License :: OSI Approved :: GNU Affero General Public License v3
Classifier: Development Status :: 4 - Beta
Requires-Python: >=3.10
Requires-Dist: odoo-addon-crm-salesperson-planner <16.1dev,>=16.0dev
Requires-Dist: odoo <16.1dev,>=16.0a
